TestObject/__init__.py
TestObject/server.py
robotframework_testobject-1.0.1.dist-info/LICENSE
robotframework_testobject-1.0.1.dist-info/METADATA
robotframework_testobject-1.0.1.dist-info/WHEEL
robotframework_testobject-1.0.1.dist-info/top_level.txt
robotframework_testobject-1.0.1.dist-info/RECORD
