Metadata-Version: 2.1
Name: robotframework-testobject
Version: 1.0.1
Summary: Simple test object for Robot Framework®
Home-page: https://github.com/imbus/robotframework-testobject
Author: imbus AG
Author-email: support@imbus.de
License: Apache 2.0 License
Platform: any
Requires-Python: >=3.8
License-File: LICENSE
Requires-Dist: robotframework >=5.0
Provides-Extra: dev
Requires-Dist: black ; extra == 'dev'
Requires-Dist: check-manifest ; extra == 'dev'
Requires-Dist: twine ; extra == 'dev'
Requires-Dist: wheel ; extra == 'dev'
Requires-Dist: setuptools ; extra == 'dev'
Requires-Dist: ruff ; extra == 'dev'
Requires-Dist: pip-tools ; extra == 'dev'
